README.md
setup.py
nzpaye/__init__.py
nzpaye/__main__.py
nzpaye/argument_parser.py
nzpaye/exception.py
nzpaye/log.py
nzpaye/main.py
nzpaye/paye.py
nzpaye/web.py
nzpaye.egg-info/PKG-INFO
nzpaye.egg-info/SOURCES.txt
nzpaye.egg-info/dependency_links.txt
nzpaye.egg-info/entry_points.txt
nzpaye.egg-info/requires.txt
nzpaye.egg-info/top_level.txt